sushy_tools/__init__.py
sushy_tools/error.py
sushy_tools/emulator/__init__.py
sushy_tools/emulator/api_utils.py
sushy_tools/emulator/auth_basic.py
sushy_tools/emulator/base.py
sushy_tools/emulator/constants.py
sushy_tools/emulator/main.py
sushy_tools/emulator/memoize.py
sushy_tools/emulator/controllers/__init__.py
sushy_tools/emulator/controllers/certificate_service.py
sushy_tools/emulator/controllers/update_service.py
sushy_tools/emulator/controllers/virtual_media.py
sushy_tools/emulator/resources/__init__.py
sushy_tools/emulator/resources/base.py
sushy_tools/emulator/resources/chassis.py
sushy_tools/emulator/resources/drives.py
sushy_tools/emulator/resources/indicators.py
sushy_tools/emulator/resources/managers.py
sushy_tools/emulator/resources/storage.py
sushy_tools/emulator/resources/vmedia.py
sushy_tools/emulator/resources/volumes.py
sushy_tools/emulator/resources/systems/__init__.py
sushy_tools/emulator/resources/systems/base.py
sushy_tools/emulator/resources/systems/fakedriver.py
sushy_tools/emulator/resources/systems/ironicdriver.py
sushy_tools/emulator/resources/systems/libvirtdriver.py
sushy_tools/emulator/resources/systems/novadriver.py
sushy_tools/emulator/templates/bios.json
sushy_tools/emulator/templates/bios_attribute_registry_file.json
sushy_tools/emulator/templates/bios_registry.json
sushy_tools/emulator/templates/bios_settings.json
sushy_tools/emulator/templates/certificate.json
sushy_tools/emulator/templates/certificate_collection.json
sushy_tools/emulator/templates/certificate_locations.json
sushy_tools/emulator/templates/certificate_service.json
sushy_tools/emulator/templates/chassis.json
sushy_tools/emulator/templates/chassis_collection.json
sushy_tools/emulator/templates/drive.json
sushy_tools/emulator/templates/error.json
sushy_tools/emulator/templates/ethernet_interface.json
sushy_tools/emulator/templates/ethernet_interfaces_collection.json
sushy_tools/emulator/templates/manager_collection.json
sushy_tools-2.2.0.dist-info/licenses/AUTHORS
sushy_tools-2.2.0.dist-info/licenses/LICENSE
sushy_tools-2.2.0.dist-info/METADATA
sushy_tools-2.2.0.dist-info/WHEEL
sushy_tools-2.2.0.dist-info/entry_points.txt
sushy_tools-2.2.0.dist-info/pbr.json
sushy_tools-2.2.0.dist-info/top_level.txt
sushy_tools-2.2.0.dist-info/RECORD
