Metadata-Version: 2.4
Name: sushy-tools
Version: 2.2.0
Summary: A set of tools to support the development and test of the Sushy library (https://docs.openstack.org/sushy/)
Home-page: https://docs.openstack.org/sushy/latest/
Author: OpenStack
Author-email: openstack-discuss@lists.openstack.org
Classifier: Environment :: OpenStack
Classifier: Intended Audience :: Information Technology
Classifier: Intended Audience :: System Administrators
Classifier: License :: OSI Approved :: Apache Software License
Classifier: Operating System :: POSIX :: Linux
Classifier: Programming Language :: Python
Classifier: Programming Language :: Python :: Implementation :: CPython
Classifier: Programming Language :: Python :: 3 :: Only
Classifier: Programming Language :: Python :: 3
Classifier: Programming Language :: Python :: 3.10
Classifier: Programming Language :: Python :: 3.11
Classifier: Programming Language :: Python :: 3.12
Requires-Python: >=3.10
License-File: LICENSE
License-File: AUTHORS
Requires-Dist: pbr>=6.0.0
Requires-Dist: Flask>=1.0.2
Requires-Dist: requests>=2.14.2
Requires-Dist: tenacity>=6.2.0
Requires-Dist: bcrypt>=3.1.3
Requires-Dist: WebOb>=1.7.1
Dynamic: author
Dynamic: author-email
Dynamic: classifier
Dynamic: description
Dynamic: home-page
Dynamic: license-file
Dynamic: requires-dist
Dynamic: requires-python
Dynamic: summary
